GWSkyNet/GWSkyNet.py
GWSkyNet/__init__.py
GWSkyNet/GWSkyNet_data/models/GWSkyNet_v2.5.1.h5
GWSkyNet/GWSkyNet_data/models/GWSkyNet_v2.5.1.json
GWSkyNet/GWSkyNet_data/models/training_norms.txt
GWSkyNet/GWSkyNet_data/rates/GWSkyNet_v2.5.1_rates.txt
GWSkyNet-2.5.2.dist-info/LICENSE
GWSkyNet-2.5.2.dist-info/METADATA
GWSkyNet-2.5.2.dist-info/WHEEL
GWSkyNet-2.5.2.dist-info/top_level.txt
GWSkyNet-2.5.2.dist-info/RECORD
