Metadata-Version: 2.1
Name: GWSkyNet
Version: 2.5.2
Summary: GWSkyNet : a machine learning algorithm used for estimating the probabiliy that a gravitational wave candidate is of astrophysical origin
Author-email: "Man Leong (Mervyn) Chan, Jess McIver, Ashish Mahabal, Daryl Haggard, Nayyer Raza" <mervync@phas.ubc.ca>, Jess McIver <mciver@phas.ubc.ca>, Ashish Mahabal <aam@astro.caltech.edu>, Daryl Haggard <daryl.haggard@mcgill.ca>, Nayyer Raza <nayyer.raza@mail.mcgill.ca>
License: GPL-2.0+
Classifier: License :: OSI Approved :: GNU General Public License v2 or later (GPLv2+)
Classifier: Programming Language :: Python
Classifier: Programming Language :: Python :: 3
Requires-Python: >=3.8
License-File: LICENSE
Requires-Dist: numpy>=1.23.2
Requires-Dist: ligo.skymap>=2.1.1
Requires-Dist: reproject>=0.8
Requires-Dist: scipy>=1.8.0
Requires-Dist: tensorflow-cpu>=2.16.1; sys_platform != "darwin"
Requires-Dist: tensorflow>=2.16.1; sys_platform == "darwin"
